[{"id":11,"name":"Иван Иванов","address":"qewq","date":"27.03.2023","status":"Выполнен","comment":"2131"},{"id":12,"name":"Иван Иванов","address":"qweq","date":"27.03.2023","status":"Выполнен","comment":"asdqwe"},{"id":13,"name":"Иван Иванов","address":"qwe","date":"27.03.2023","status":"Выполнен","comment":"qweqw"},{"id":18,"name":"Иван Иванов","address":"qwe","date":"27.03.2023","status":"Выполнен","comment":"qweqw"},{"id":19,"name":"Иван Иванов","address":"qwe","date":"27.03.2023","status":"Выполнен","comment":"qwewq"},{"id":20,"name":"Иван Иванов","address":"qwe","date":"25.03.2023","status":"Выполнен","comment":"qwewq"},{"id":21,"name":"Иван Иванов","address":"qqq","date":"27.03.2023","status":"Выполнен","comment":"qqq"},{"id":23,"name":"Иван Ивановqweqw","address":"asda","date":"27.03.2023","status":"Выполнен","comment":"qweqw"},{"id":25,"name":"Иван Иванов","address":"qwe","date":"27.03.2023","status":"Выполнен","comment":"qweq"},{"id":26,"name":"Иван Иванов","address":"qwe","date":"27.03.2023","status":"Выполнен","comment":"qweqw"},{"id":27,"name":"Иван Иванов","address":"qwe","date":"27.03.2023","status":"Выполнен","comment":"qweqw"},{"id":28,"name":"Иван Иванов","address":"qwe","date":"27.03.2023","status":"Выполнен","comment":"qweqw"},{"id":33,"name":"Иван Иванов","address":"q","date":"27.03.2023","status":"Выполнен","comment":"q"},{"id":34,"name":"Иван Иванов","address":"qweqw","date":"27.03.2023","status":"Выполнен","comment":"qweqw"}]